acp_cli/__init__.py
acp_cli/acp_compiler/__init__.py
acp_cli/acp_compiler/acp_ast.py
acp_cli/acp_compiler/acp_grammar.lark
acp_cli/acp_compiler/acp_module_loader.py
acp_cli/acp_compiler/acp_module_resolver.py
acp_cli/acp_compiler/acp_normalizer.py
acp_cli/acp_compiler/acp_parser.py
acp_cli/acp_compiler/acp_resolver.py
acp_cli/acp_compiler/acp_validator.py
acp_cli/acp_compiler/compiler.py
acp_cli/acp_compiler/credentials.py
acp_cli/acp_compiler/ir_generator.py
acp_cli/acp_compiler/parser.py
acp_cli/acp_compiler/py.typed
acp_cli/acp_compiler/validator.py
acp_cli/acp_mcp/__init__.py
acp_cli/acp_mcp/client.py
acp_cli/acp_mcp/py.typed
acp_cli/acp_mcp/server.py
acp_cli/acp_mcp/types.py
acp_cli/acp_runtime/__init__.py
acp_cli/acp_runtime/approval.py
acp_cli/acp_runtime/engine.py
acp_cli/acp_runtime/llm.py
acp_cli/acp_runtime/logging_config.py
acp_cli/acp_runtime/policy.py
acp_cli/acp_runtime/py.typed
acp_cli/acp_runtime/state.py
acp_cli/acp_runtime/tracing.py
acp_cli/acp_schema/__init__.py
acp_cli/acp_schema/ir.py
acp_cli/acp_schema/models.py
acp_cli/acp_schema/py.typed
acp_cli/acp_schema/version.py
acp_cli/commands/__init__.py
acp_cli/commands/compile.py
acp_cli/commands/init.py
acp_cli/commands/run.py
acp_cli/commands/validate.py
acp_cli/main.py
acp_cli-0.0.804.dist-info/METADATA
acp_cli-0.0.804.dist-info/WHEEL
acp_cli-0.0.804.dist-info/entry_points.txt
acp_cli-0.0.804.dist-info/RECORD
